PyFaceLib/__init__.py
PyFaceLib/face_alignment.py
PyFaceLib/face_detection.py
PyFaceLib/face_emotion_recognition.py
PyFaceLib/face_normalization.py
PyFaceLib/representation_extraction.py
pyfacelib-0.0.3.dist-info/METADATA
pyfacelib-0.0.3.dist-info/WHEEL
pyfacelib-0.0.3.dist-info/top_level.txt
pyfacelib-0.0.3.dist-info/RECORD
