Metadata-Version: 2.1
Name: pyfacelib
Version: 0.0.3
Summary: Python High Level Face Tools Library
Author: SAlirezaMousavizade
Author-email: s.a.mosavizade@gmail.com
Keywords: Detection,Recognition,Alignment,Normalization,Emotion,Sentiment,Face Detection,Face Recognition,Face Alignment,Face Normalization,Face Emotion,Face Sentiment
